{
  "id_escena": "escena_02",
  "query_usada": "town square crowd ambience",
  "pista_principal": {
    "url_preview": "https://cdn.freesound.org/previews/752/752092_9034501-hq.mp3",
    "titulo": "240730_220854_FR_Crowd_outdoor",
    "autor": "kevp888",
    "duracion_segundos": 241.1,
    "loop": true,
    "volumen": 0.6
  },
  "pista_fallback": {
    "url_preview": "https://cdn.freesound.org/previews/344/344767_1648170-hq.mp3",
    "titulo": "shoppingstreet on 50m kerkplein 03 160409_21.flac",
    "autor": "klankbeeld",
    "duracion_segundos": 853.1,
    "loop": true,
    "volumen": 0.6
  },
  "fuente": "freesound"
}